README.txt
setup.py
sven/__init__.py
sven/backend.py
sven/bzr.py
sven/exc.py
sven/path_fixer.py
sven/simple_backend.py
sven.egg-info/PKG-INFO
sven.egg-info/SOURCES.txt
sven.egg-info/dependency_links.txt
sven.egg-info/entry_points.txt
sven.egg-info/not-zip-safe
sven.egg-info/top_level.txt