Metadata-Version: 1.0
Name: sven
Version: 0.9
Summary: sven is a document-oriented programming library that helps you put content in a version-controlled document repository
Home-page: UNKNOWN
Author: Ethan Jucovy & Jeff Hammel
Author-email: ejucovy@gmail.com
License: GPL
Platform: UNKNOWN
